summarynb/__init__.py
summarynb/cli.py
summarynb-0.1.4.dist-info/LICENSE
summarynb-0.1.4.dist-info/METADATA
summarynb-0.1.4.dist-info/WHEEL
summarynb-0.1.4.dist-info/entry_points.txt
summarynb-0.1.4.dist-info/top_level.txt
summarynb-0.1.4.dist-info/RECORD
