Metadata-Version: 2.1
Name: summarynb
Version: 0.1.4
Summary: Helpers to create summary Jupyter notebooks.
Home-page: https://github.com/maximz/summarynb
Author: Maxim Zaslavsky
Author-email: maxim@maximz.com
License: MIT license
Keywords: summarynb
Platform: UNKNOWN
Classifier: Development Status :: 2 - Pre-Alpha
Classifier: Intended Audience :: Developers
Classifier: License :: OSI Approved :: MIT License
Classifier: Natural Language :: English
Classifier: Programming Language :: Python :: 3
Classifier: Programming Language :: Python :: 3.6
Classifier: Programming Language :: Python :: 3.7
Classifier: Programming Language :: Python :: 3.8
Requires-Python: >=3.6
License-File: LICENSE
Requires-Dist: Click (>=7.0)
Requires-Dist: IPython
Requires-Dist: pandas
Requires-Dist: nbexec
